temptree.py
temptree-0.2.1.dist-info/LICENSE.md
temptree-0.2.1.dist-info/WHEEL
temptree-0.2.1.dist-info/METADATA
temptree-0.2.1.dist-info/RECORD
