Metadata-Version: 2.1
Name: temptree
Version: 0.2.1
Summary: Generates temporary files and directories from a tree
Home-page: https://github.com/neimad/temptree
License: GPL-3.0-or-later
Keywords: temporary,filesystem,doctest
Author: Damien Flament
Author-email: damien.flament@gmx.com
Requires-Python: >=3.6,<3.8
Classifier: Intended Audience :: Developers
Classifier: License :: OSI Approved :: GNU General Public License v3 or later (GPLv3+)
Classifier: Operating System :: OS Independent
Classifier: Programming Language :: Python :: 3
Classifier: Programming Language :: Python :: 3.6
Classifier: Programming Language :: Python :: 3.7
Classifier: Topic :: Software Development :: Testing
Classifier: Topic :: System :: Filesystems
Project-URL: Documentation, https://neimad.github.io/temptree
Project-URL: Repository, https://github.com/neimad/temptree
